lscript/__init__.py
lscript/__main__.py
lscript/cli.py
lscript/plugins.py
lscript/runner.py
lscript/shell.py
lscript/explain/__init__.py
lscript/explain/base.py
lscript/explain/rules.py
lscript/ui/__init__.py
lscript/ui/formatter.py
lscript/ui/theme.py
lscript_terminal-0.2.2.dist-info/licenses/LICENSE
lscript_terminal-0.2.2.dist-info/METADATA
lscript_terminal-0.2.2.dist-info/WHEEL
lscript_terminal-0.2.2.dist-info/entry_points.txt
lscript_terminal-0.2.2.dist-info/top_level.txt
lscript_terminal-0.2.2.dist-info/RECORD
