Metadata-Version: 2.4
Name: lscript-terminal
Version: 0.2.2
Summary: Terminal intelligent orienté humain - Explique les erreurs en langage simple
Author-email: LScript Team <contact@lscript.fr>
Maintainer-email: LScript Team <contact@lscript.fr>
License: MIT
Project-URL: Homepage, https://lscript.fr
Project-URL: Documentation, https://lscript.fr/docs
Project-URL: Repository, https://github.com/lscript/lscript
Project-URL: Changelog, https://github.com/lscript/lscript/blob/main/CHANGELOG.md
Project-URL: Bug Tracker, https://github.com/lscript/lscript/issues
Keywords: terminal,shell,error-handling,developer-tools,cli,human-friendly,beginner-friendly
Classifier: Development Status :: 4 - Beta
Classifier: Environment :: Console
Classifier: Intended Audience :: Developers
Classifier: Intended Audience :: Education
Classifier: License :: OSI Approved :: MIT License
Classifier: Operating System :: POSIX :: Linux
Classifier: Operating System :: MacOS
Classifier: Operating System :: Microsoft :: Windows
Classifier: Programming Language :: Python :: 3
Classifier: Programming Language :: Python :: 3.9
Classifier: Programming Language :: Python :: 3.10
Classifier: Programming Language :: Python :: 3.11
Classifier: Programming Language :: Python :: 3.12
Classifier: Programming Language :: Python :: 3.13
Classifier: Topic :: System :: Shells
Classifier: Topic :: Utilities
Classifier: Topic :: Software Development
Classifier: Typing :: Typed
Requires-Python: >=3.9
License-File: LICENSE
Provides-Extra: ui
Requires-Dist: rich>=13.0.0; extra == "ui"
Provides-Extra: full
Requires-Dist: rich>=13.0.0; extra == "full"
Provides-Extra: dev
Requires-Dist: rich>=13.0.0; extra == "dev"
Requires-Dist: pytest>=7.0.0; extra == "dev"
Requires-Dist: pytest-cov>=4.0.0; extra == "dev"
Requires-Dist: mypy>=1.0.0; extra == "dev"
Requires-Dist: ruff>=0.1.0; extra == "dev"
Dynamic: license-file
